zipline_polygon_bundle/__init__.py
zipline_polygon_bundle/adjustments.py
zipline_polygon_bundle/bundle.py
zipline_polygon_bundle/compute_signals.py
zipline_polygon_bundle/concat_all_aggs.py
zipline_polygon_bundle/concat_all_aggs_partitioned.py
zipline_polygon_bundle/config.py
zipline_polygon_bundle/nyse_all_hours_calendar.py
zipline_polygon_bundle/polygon_file_reader.py
zipline_polygon_bundle/process_all_aggs.py
zipline_polygon_bundle/quotes.py
zipline_polygon_bundle/split_aggs_by_ticker.py
zipline_polygon_bundle/tickers_and_names.py
zipline_polygon_bundle/trades.py
zipline_polygon_bundle-0.2.4.dist-info/LICENSE
zipline_polygon_bundle-0.2.4.dist-info/METADATA
zipline_polygon_bundle-0.2.4.dist-info/WHEEL
zipline_polygon_bundle-0.2.4.dist-info/RECORD
