Metadata-Version: 2.3
Name: zipline_polygon_bundle
Version: 0.2.4
Summary: A zipline-reloaded data provider bundle for Polygon.io
License: GNU AFFERO GENERAL PUBLIC LICENSE
Keywords: zipline,data-bundle,finance
Author: Jim White
Author-email: jim@fovi.com
Requires-Python: >= 3.10,<4.0
Classifier: Programming Language :: Python :: 3
Classifier: License :: OSI Approved :: GNU Affero General Public License v3
Classifier: Operating System :: OS Independent
Requires-Dist: bcolz-zipline (>=1.2.11)
Requires-Dist: filelock (>=3.16.0)
Requires-Dist: fsspec (>=2024.10)
Requires-Dist: numpy (<2)
Requires-Dist: pandas (>=2.2,<3)
Requires-Dist: polygon-api-client (>=1.14.2)
Requires-Dist: pyarrow (>=18.1.0,<19)
Requires-Dist: pytz (>=2018.5)
Requires-Dist: requests (>=2.9.1)
Requires-Dist: toolz (>=0.8.2)
Requires-Dist: zipline-arrow (>=3.2.2)
Project-URL: Repository, https://github.com/fovi-llc/zipline-polygon-bundle
